{
  "version": "0.2",
  "ignorePaths": [
    "pnpm-lock.yaml",
    "src/components.d.ts"
  ],
  "dictionaryDefinitions": [],
  "dictionaries": [
    "en-gb",
    "softwareTerms",
    "typescript",
    "npm",
    "fonts",
    "css",
    "node"
  ],
  "words": [
    "antfu",
    "Chronomancer",
    "composables",
    "demi",
    "Elementalist",
    "Frostgrave",
    "iconify",
    "intlify",
    "nprogress",
    "pinia",
    "pnpm",
    "shiki",
    "shikijs",
    "Sigilist",
    "sizecheck",
    "taze",
    "typecheck",
    "unhead",
    "unocss",
    "unplugin",
    "Vite",
    "vitejs",
    "Vitesse",
    "vitest",
    "vuetify",
    "vueuse",
    "warband",
    "warbands",
    "webfont"
  ],
  "ignoreWords": [],
  "import": []
}
